rust_std_t_x64_win_msvc_nightly_p1/__init__.py
rust_std_t_x64_win_msvc_nightly_p1/data/COPYRIGHT
rust_std_t_x64_win_msvc_nightly_p1/data/LICENSE-APACHE
rust_std_t_x64_win_msvc_nightly_p1/data/LICENSE-MIT
rust_std_t_x64_win_msvc_nightly_p1/data/README.md
rust_std_t_x64_win_msvc_nightly_p1/data/builder-config
rust_std_t_x64_win_msvc_nightly_p1/data/components
rust_std_t_x64_win_msvc_nightly_p1/data/git-commit-hash
rust_std_t_x64_win_msvc_nightly_p1/data/git-commit-info
rust_std_t_x64_win_msvc_nightly_p1/data/install.sh
rust_std_t_x64_win_msvc_nightly_p1/data/rust-installer-version
rust_std_t_x64_win_msvc_nightly_p1/data/version
rust_std_t_x64_win_msvc_nightly_p1/data/rust-std-x86_64-pc-windows-msvc/manifest.in
rust_std_t_x64_win_msvc_nightly_p1/data/rust-std-x86_64-pc-windows-msvc/lib/rustlib/x86_64-pc-windows-msvc/lib/liballoc-7d78dc9d6339b492.rlib
rust_std_t_x64_win_msvc_nightly_p1/data/rust-std-x86_64-pc-windows-msvc/lib/rustlib/x86_64-pc-windows-msvc/lib/libcfg_if-a1bbe7acc6c12aa0.rlib
rust_std_t_x64_win_msvc_nightly_p1/data/rust-std-x86_64-pc-windows-msvc/lib/rustlib/x86_64-pc-windows-msvc/lib/libcompiler_builtins-7ba6bbd2ee3b083b.rlib
rust_std_t_x64_win_msvc_nightly_p1/data/rust-std-x86_64-pc-windows-msvc/lib/rustlib/x86_64-pc-windows-msvc/lib/libcore-bff5120e63f2e11b.rlib
rust_std_t_x64_win_msvc_nightly_p1/data/rust-std-x86_64-pc-windows-msvc/lib/rustlib/x86_64-pc-windows-msvc/lib/libgetopts-7770f15d0b5c38b0.rlib
rust_std_t_x64_win_msvc_nightly_p1/data/rust-std-x86_64-pc-windows-msvc/lib/rustlib/x86_64-pc-windows-msvc/lib/libhashbrown-51e6f59991e860db.rlib
rust_std_t_x64_win_msvc_nightly_p1/data/rust-std-x86_64-pc-windows-msvc/lib/rustlib/x86_64-pc-windows-msvc/lib/libproc_macro-daf22db425d883d9.rlib
rust_std_t_x64_win_msvc_nightly_p1/data/rust-std-x86_64-pc-windows-msvc/lib/rustlib/x86_64-pc-windows-msvc/lib/libprofiler_builtins-55c7f3e209910597.rlib
rust_std_t_x64_win_msvc_nightly_p1-1.91.0.dist-info/METADATA
rust_std_t_x64_win_msvc_nightly_p1-1.91.0.dist-info/WHEEL
rust_std_t_x64_win_msvc_nightly_p1-1.91.0.dist-info/top_level.txt
rust_std_t_x64_win_msvc_nightly_p1-1.91.0.dist-info/RECORD
