Metadata-Version: 2.4
Name: rust_std_t_x64_win_msvc_nightly_p1
Version: 1.91.0
Summary: Segment rust-std.target.x86_64-pc-windows-msvc part p1
License: MIT
